parselite/__init__.py
parselite/_arxiv_latex.py
parselite/html_parser.py
parselite/main.py
parselite/yt_parser.py
parselite-0.3.13.dist-info/LICENSE
parselite-0.3.13.dist-info/METADATA
parselite-0.3.13.dist-info/WHEEL
parselite-0.3.13.dist-info/top_level.txt
parselite-0.3.13.dist-info/RECORD
