Metadata-Version: 2.1
Name: parselite
Version: 0.3.13
Summary: A powerful web content fetcher and processor
Home-page: https://github.com/yourusername/pyopengenai
Author: Kammari Santhosh
Author-email: Your Name <your.email@example.com>
Project-URL: Homepage, https://github.com/yourusername/pyopengenai
Project-URL: Bug Tracker, https://github.com/yourusername/pyopengenai/issues
Classifier: Programming Language :: Python :: 3
Classifier: License :: OSI Approved :: MIT License
Classifier: Operating System :: OS Independent
Requires-Python: >=3.7
License-File: LICENSE
Requires-Dist: selenium==4.25.0
Requires-Dist: beautifulsoup4
Requires-Dist: requests
Requires-Dist: aiohttp
Requires-Dist: trafilatura
Requires-Dist: youtube-transcript-api
